setup.py
qscollect/__init__.py
qscollect/collectors/__init__.py
qscollect/collectors/contrib/__init__.py
qscollect/collectors/contrib/qswithings.py
qscollect_withings.egg-info/PKG-INFO
qscollect_withings.egg-info/SOURCES.txt
qscollect_withings.egg-info/dependency_links.txt
qscollect_withings.egg-info/namespace_packages.txt
qscollect_withings.egg-info/requires.txt
qscollect_withings.egg-info/top_level.txt