Metadata-Version: 1.0
Name: qscollect-withings
Version: 0.1.2
Summary: A qscollect collector for WiThings Weight
Home-page: http://bitbucket.org/russellhay/qscollect-withings
Author: Russell Hay
Author-email: me@russellhay.com
License: UNKNOWN
Platform: UNKNOWN
